whenfin
